picsellia_tf2/__init__.py
picsellia_tf2/object_detection/CONTRIBUTING.md
picsellia_tf2/object_detection/README.md
picsellia_tf2/object_detection/__init__.py
picsellia_tf2/object_detection/anchor_generators/__init__.py
picsellia_tf2/object_detection/anchor_generators/flexible_grid_anchor_generator.py
picsellia_tf2/object_detection/anchor_generators/flexible_grid_anchor_generator_test.py
picsellia_tf2/object_detection/anchor_generators/grid_anchor_generator.py
picsellia_tf2/object_detection/anchor_generators/grid_anchor_generator_test.py
picsellia_tf2/object_detection/anchor_generators/multiple_grid_anchor_generator.py
picsellia_tf2/object_detection/anchor_generators/multiple_grid_anchor_generator_test.py
picsellia_tf2/object_detection/anchor_generators/multiscale_grid_anchor_generator.py
picsellia_tf2/object_detection/anchor_generators/multiscale_grid_anchor_generator_test.py
picsellia_tf2/object_detection/box_coders/__init__.py
picsellia_tf2/object_detection/box_coders/faster_rcnn_box_coder.py
picsellia_tf2/object_detection/box_coders/faster_rcnn_box_coder_test.py
picsellia_tf2/object_detection/box_coders/keypoint_box_coder.py
picsellia_tf2/object_detection/box_coders/keypoint_box_coder_test.py
picsellia_tf2/object_detection/box_coders/mean_stddev_box_coder.py
picsellia_tf2/object_detection/box_coders/mean_stddev_box_coder_test.py
picsellia_tf2/object_detection/box_coders/square_box_coder.py
picsellia_tf2/object_detection/box_coders/square_box_coder_test.py
picsellia_tf2/object_detection/builders/__init__.py
picsellia_tf2/object_detection/builders/anchor_generator_builder.py
picsellia_tf2/object_detection/builders/anchor_generator_builder_test.py
picsellia_tf2/object_detection/builders/box_coder_builder.py
picsellia_tf2/object_detection/builders/box_coder_builder_test.py
picsellia_tf2/object_detection/builders/box_predictor_builder.py
picsellia_tf2/object_detection/builders/box_predictor_builder_test.py
picsellia_tf2/object_detection/builders/calibration_builder.py
picsellia_tf2-0.11.10.dist-info/METADATA
picsellia_tf2-0.11.10.dist-info/WHEEL
picsellia_tf2-0.11.10.dist-info/RECORD
